{
  "types" : [
    {
      "fields" : [
        {
          "args" : [

          ],
          "name" : "address_id",
          "type" : {
            "kind" : "NON_NULL",
            "ofType" : {
              "kind" : "SCALAR",
              "name" : "bigint"
            }
          },
          "isDeprecated" : false
        },
        {
          "args" : [

          ],
          "name" : "country",
          "type" : {
            "kind" : "SCALAR",
            "name" : "String"
          },
          "isDeprecated" : false
        },
        {
          "args" : [

          ],
          "name" : "line_1_number_building",
          "type" : {
            "kind" : "SCALAR",
            "name" : "String"
          },
          "isDeprecated" : false
        },
        {
          "isDeprecated" : false,
          "args" : [
            {
              "name" : "distinct_on",
              "type" : {
                "kind" : "LIST",
                "ofType" : {
                  "kind" : "NON_NULL",
                  "ofType" : {
                    "kind" : "ENUM",
                    "name" : "party_addresses_select_column"
                  }
                }
              },
              "description" : "distinct select on columns"
            },
            {
              "name" : "limit",
              "type" : {
                "kind" : "SCALAR",
                "name" : "Int"
              },
              "description" : "limit the number of rows returned"
            },
            {
              "name" : "offset",
              "type" : {
                "kind" : "SCALAR",
                "name" : "Int"
              },
              "description" : "skip the first n rows. Use only with order_by"
            },
            {
              "name" : "order_by",
              "type" : {
                "kind" : "LIST",
                "ofType" : {
                  "kind" : "NON_NULL",
                  "ofType" : {
                    "kind" : "INPUT_OBJECT",
                    "name" : "party_addresses_order_by"
                  }
                }
              },
              "description" : "sort the rows by one or more columns"
            },
            {
              "name" : "where",
              "type" : {
                "kind" : "INPUT_OBJECT",
                "name" : "party_addresses_bool_exp"
              },
              "description" : "filter the rows returned"
            }
          ],
          "name" : "party_addresses",
          "description" : "An array relationship",
          "type" : {
            "kind" : "NON_NULL",
            "ofType" : {
              "kind" : "LIST",
              "ofType" : {
                "kind" : "NON_NULL",
                "ofType" : {
                  "kind" : "OBJECT",
                  "name" : "party_addresses"
                }
              }
            }
          }
        },
        {
          "isDeprecated" : false,
          "args" : [
            {
              "name" : "distinct_on",
              "type" : {
                "kind" : "LIST",
                "ofType" : {
                  "kind" : "NON_NULL",
                  "ofType" : {
                    "kind" : "ENUM",
                    "name" : "party_addresses_select_column"
                  }
                }
              },
              "description" : "distinct select on columns"
            },
            {
              "name" : "limit",
              "type" : {
                "kind" : "SCALAR",
                "name" : "Int"
              },
              "description" : "limit the number of rows returned"
            },
            {
              "name" : "offset",
              "type" : {
                "kind" : "SCALAR",
                "name" : "Int"
              },
              "description" : "skip the first n rows. Use only with order_by"
            },
            {
              "name" : "order_by",
              "type" : {
                "kind" : "LIST",
                "ofType" : {
                  "kind" : "NON_NULL",
                  "ofType" : {
                    "kind" : "INPUT_OBJECT",
                    "name" : "party_addresses_order_by"
                  }
                }
              },
              "description" : "sort the rows by one or more columns"
            },
            {
              "name" : "where",
              "type" : {
                "kind" : "INPUT_OBJECT",
                "name" : "party_addresses_bool_exp"
              },
              "description" : "filter the rows returned"
            }
          ],
          "name" : "party_addresses_aggregate",
          "description" : "An aggregated array relationship",
          "type" : {
            "kind" : "NON_NULL",
            "ofType" : {
              "kind" : "OBJECT",
              "name" : "party_addresses_aggregate"
            }
          }
        },
        {
          "args" : [

          ],
          "name" : "state_province_county",
          "type" : {
            "kind" : "SCALAR",
            "name" : "String"
          },
          "isDeprecated" : false
        },
        {
          "args" : [

          ],
          "name" : "town_city",
          "type" : {
            "kind" : "SCALAR",
            "name" : "String"
          },
          "isDeprecated" : false
        },
        {
          "args" : [

          ],
          "name" : "zip_postcode",
          "type" : {
            "kind" : "SCALAR",
            "name" : "String"
          },
          "isDeprecated" : false
        }
      ],
      "kind" : "OBJECT",
      "name" : "addresses",
      "description" : "columns and relationships of \"addresses\""
    },
    {
      "fields" : [
        {
          "args" : [

          ],
          "name" : "aggregate",
          "type" : {
            "kind" : "OBJECT",
            "name" : "addresses_aggregate_fields"
          },
          "isDeprecated" : false
        },
        {
          "args" : [

          ],
          "name" : "nodes",
          "type" : {
            "kind" : "NON_NULL",
            "ofType" : {
              "kind" : "LIST",
              "ofType" : {
                "kind" : "NON_NULL",
                "ofType" : {
                  "kind" : "OBJECT",
                  "name" : "addresses"
                }
              }
            }
          },
          "isDeprecated" : false
        }
      ],
      "kind" : "OBJECT",
      "name" : "addresses_aggregate",
      "description" : "aggregated selection of \"addresses\""
    },
    {
      "fields" : [
        {
          "args" : [

          ],
          "name" : "form_description",
          "type" : {
            "kind" : "SCALAR",
            "name" : "String"
          },
          "isDeprecated" : false
        },
        {
          "args" : [

          ],
          "name" : "form_id",
          "type" : {
            "kind" : "NON_NULL",
            "ofType" : {
              "kind" : "SCALAR",
              "name" : "bigint"
            }
          },
          "isDeprecated" : false
        },
        {
          "args" : [

          ],
          "name" : "form_name",
          "type" : {
            "kind" : "SCALAR",
            "name" : "String"
          },
          "isDeprecated" : false
        },
        {
          "args" : [

          ],
          "name" : "form_number",
          "type" : {
            "kind" : "SCALAR",
            "name" : "String"
          },
          "isDeprecated" : false
        },
        {
          "args" : [

          ],
          "name" : "form_type_code",
          "type" : {
            "kind" : "SCALAR",
            "name" : "String"
          },
          "isDeprecated" : false
        },
        {
          "isDeprecated" : false,
          "args" : [
            {
              "name" : "distinct_on",
              "type" : {
                "kind" : "LIST",
                "ofType" : {
                  "kind" : "NON_NULL",
                  "ofType" : {
                    "kind" : "ENUM",
                    "name" : "party_forms_select_column"
                  }
                }
              },
              "description" : "distinct select on columns"
            },
            {
              "name" : "limit",
              "type" : {
                "kind" : "SCALAR",
                "name" : "Int"
              },
              "description" : "limit the number of rows returned"
            },
            {
              "name" : "offset",
              "type" : {
                "kind" : "SCALAR",
                "name" : "Int"
              },
              "description" : "skip the first n rows. Use only with order_by"
            },
            {
              "name" : "order_by",
              "type" : {
                "kind" : "LIST",
                "ofType" : {
                  "kind" : "NON_NULL",
                  "ofType" : {
                    "kind" : "INPUT_OBJECT",
                    "name" : "party_forms_order_by"
                  }
                }
              },
              "description" : "sort the rows by one or more columns"
            },
            {
              "name" : "where",
              "type" : {
                "kind" : "INPUT_OBJECT",
                "name" : "party_forms_bool_exp"
              },
              "description" : "filter the rows returned"
            }
          ],
          "name" : "party_forms",
          "description" : "An array relationship",
          "type" : {
            "kind" : "NON_NULL",
            "ofType" : {
              "kind" : "LIST",
              "ofType" : {
                "kind" : "NON_NULL",
                "ofType" : {
                  "kind" : "OBJECT",
                  "name" : "party_forms"
                }
              }
            }
          }
        },
        {
          "isDeprecated" : false,
          "args" : [
            {
              "name" : "distinct_on",
              "type" : {
                "kind" : "LIST",
                "ofType" : {
                  "kind" : "NON_NULL",
                  "ofType" : {
                    "kind" : "ENUM",
                    "name" : "party_forms_select_column"
                  }
                }
              },
              "description" : "distinct select on columns"
            },
            {
              "name" : "limit",
              "type" : {
                "kind" : "SCALAR",
                "name" : "Int"
              },
              "description" : "limit the number of rows returned"
            },
            {
              "name" : "offset",
              "type" : {
                "kind" : "SCALAR",
                "name" : "Int"
              },
              "description" : "skip the first n rows. Use only with order_by"
            },
            {
              "name" : "order_by",
              "type" : {
                "kind" : "LIST",
                "ofType" : {
                  "kind" : "NON_NULL",
                  "ofType" : {
                    "kind" : "INPUT_OBJECT",
                    "name" : "party_forms_order_by"
                  }
                }
              },
              "description" : "sort the rows by one or more columns"
            },
            {
              "name" : "where",
              "type" : {
                "kind" : "INPUT_OBJECT",
                "name" : "party_forms_bool_exp"
              },
              "description" : "filter the rows returned"
            }
          ],
          "name" : "party_forms_aggregate",
          "description" : "An aggregated array relationship",
          "type" : {
            "kind" : "NON_NULL",
            "ofType" : {
              "kind" : "OBJECT",
              "name" : "party_forms_aggregate"
            }
          }
        },
        {
          "isDeprecated" : false,
          "args" : [

          ],
          "name" : "service",
          "description" : "An object relationship",
          "type" : {
            "kind" : "OBJECT",
            "name" : "services"
          }
        },
        {
          "args" : [

          ],
          "name" : "service_id",
          "type" : {
            "kind" : "SCALAR",
            "name" : "bigint"
          },
          "isDeprecated" : false
        }
      ],
      "kind" : "OBJECT",
      "name" : "forms",
      "description" : "columns and relationships of \"forms\""
    },
    {
      "fields" : [
        {
          "args" : [

          ],
          "name" : "aggregate",
          "type" : {
            "kind" : "OBJECT",
            "name" : "forms_aggregate_fields"
          },
          "isDeprecated" : false
        },
        {
          "args" : [

          ],
          "name" : "nodes",
          "type" : {
            "kind" : "NON_NULL",
            "ofType" : {
              "kind" : "LIST",
              "ofType" : {
                "kind" : "NON_NULL",
                "ofType" : {
                  "kind" : "OBJECT",
                  "name" : "forms"
                }
              }
            }
          },
          "isDeprecated" : false
        }
      ],
      "kind" : "OBJECT",
      "name" : "forms_aggregate",
      "description" : "aggregated selection of \"forms\""
    },
    {
      "fields" : [
        {
          "args" : [

          ],
          "name" : "individual_address",
          "type" : {
            "kind" : "SCALAR",
            "name" : "String"
          },
          "isDeprecated" : false
        },
        {
          "args" : [

          ],
          "name" : "individual_email",
          "type" : {
            "kind" : "SCALAR",
            "name" : "String"
          },
          "isDeprecated" : false
        },
        {
          "args" : [

          ],
          "name" : "individual_first_name",
          "type" : {
            "kind" : "SCALAR",
            "name" : "String"
          },
          "isDeprecated" : false
        },
        {
          "args" : [

          ],
          "name" : "individual_id",
          "type" : {
            "kind" : "NON_NULL",
            "ofType" : {
              "kind" : "SCALAR",
              "name" : "bigint"
            }
          },
          "isDeprecated" : false
        },
        {
          "args" : [

          ],
          "name" : "individual_last_name",
          "type" : {
            "kind" : "SCALAR",
            "name" : "String"
          },
          "isDeprecated" : false
        },
        {
          "args" : [

          ],
          "name" : "individual_middle_name",
          "type" : {
            "kind" : "SCALAR",
            "name" : "String"
          },
          "isDeprecated" : false
        },
        {
          "args" : [

          ],
          "name" : "inidividual_phone",
          "type" : {
            "kind" : "SCALAR",
            "name" : "String"
          },
          "isDeprecated" : false
        },
        {
          "isDeprecated" : false,
          "args" : [
            {
              "name" : "distinct_on",
              "type" : {
                "kind" : "LIST",
                "ofType" : {
                  "kind" : "NON_NULL",
                  "ofType" : {
                    "kind" : "ENUM",
                    "name" : "organization_contact_individuals_select_column"
                  }
                }
              },
              "description" : "distinct select on columns"
            },
            {
              "name" : "limit",
              "type" : {
                "kind" : "SCALAR",
                "name" : "Int"
              },
              "description" : "limit the number of rows returned"
            },
            {
              "name" : "offset",
              "type" : {
                "kind" : "SCALAR",
                "name" : "Int"
              },
              "description" : "skip the first n rows. Use only with order_by"
            },
            {
              "name" : "order_by",
              "type" : {
                "kind" : "LIST",
                "ofType" : {
                  "kind" : "NON_NULL",
                  "ofType" : {
                    "kind" : "INPUT_OBJECT",
                    "name" : "organization_contact_individuals_order_by"
                  }
                }
              },
              "description" : "sort the rows by one or more columns"
            },
            {
              "name" : "where",
              "type" : {
                "kind" : "INPUT_OBJECT",
                "name" : "organization_contact_individuals_bool_exp"
              },
              "description" : "filter the rows returned"
            }
          ],
          "name" : "organization_contact_individuals",
          "description" : "An array relationship",
          "type" : {
            "kind" : "NON_NULL",
            "ofType" : {
              "kind" : "LIST",
              "ofType" : {
                "kind" : "NON_NULL",
                "ofType" : {
                  "kind" : "OBJECT",
                  "name" : "organization_contact_individuals"
                }
              }
            }
          }
        },
        {
          "isDeprecated" : false,
          "args" : [
            {
              "name" : "distinct_on",
              "type" : {
                "kind" : "LIST",
                "ofType" : {
                  "kind" : "NON_NULL",
                  "ofType" : {
                    "kind" : "ENUM",
                    "name" : "organization_contact_individuals_select_column"
                  }
                }
              },
              "description" : "distinct select on columns"
            },
            {
              "name" : "limit",
              "type" : {
                "kind" : "SCALAR",
                "name" : "Int"
              },
              "description" : "limit the number of rows returned"
            },
            {
              "name" : "offset",
              "type" : {
                "kind" : "SCALAR",
                "name" : "Int"
              },
              "description" : "skip the first n rows. Use only with order_by"
            },
            {
              "name" : "order_by",
              "type" : {
                "kind" : "LIST",
                "ofType" : {
                  "kind" : "NON_NULL",
                  "ofType" : {
                    "kind" : "INPUT_OBJECT",
                    "name" : "organization_contact_individuals_order_by"
                  }
                }
              },
              "description" : "sort the rows by one or more columns"
            },
            {
              "name" : "where",
              "type" : {
                "kind" : "INPUT_OBJECT",
                "name" : "organization_contact_individuals_bool_exp"
              },
              "description" : "filter the rows returned"
            }
          ],
          "name" : "organization_contact_individuals_aggregate",
          "description" : "An aggregated array relationship",
          "type" : {
            "kind" : "NON_NULL",
            "ofType" : {
              "kind" : "OBJECT",
              "name" : "organization_contact_individuals_aggregate"
            }
          }
        }
      ],
      "kind" : "OBJECT",
      "name" : "individuals",
      "description" : "columns and relationships of \"individuals\""
    },
    {
      "fields" : [
        {
          "args" : [

          ],
          "name" : "aggregate",
          "type" : {
            "kind" : "OBJECT",
            "name" : "individuals_aggregate_fields"
          },
          "isDeprecated" : false
        },
        {
          "args" : [

          ],
          "name" : "nodes",
          "type" : {
            "kind" : "NON_NULL",
            "ofType" : {
              "kind" : "LIST",
              "ofType" : {
                "kind" : "NON_NULL",
                "ofType" : {
                  "kind" : "OBJECT",
                  "name" : "individuals"
                }
              }
            }
          },
          "isDeprecated" : false
        }
      ],
      "kind" : "OBJECT",
      "name" : "individuals_aggregate",
      "description" : "aggregated selection of \"individuals\""
    },
    {
      "fields" : [
        {
          "args" : [

          ],
          "name" : "date_contact_from",
          "type" : {
            "kind" : "SCALAR",
            "name" : "timestamptz"
          },
          "isDeprecated" : false
        },
        {
          "args" : [

          ],
          "name" : "date_contact_to",
          "type" : {
            "kind" : "SCALAR",
            "name" : "timestamptz"
          },
          "isDeprecated" : false
        },
        {
          "isDeprecated" : false,
          "args" : [

          ],
          "name" : "individual",
          "description" : "An object relationship",
          "type" : {
            "kind" : "NON_NULL",
            "ofType" : {
              "kind" : "OBJECT",
              "name" : "individuals"
            }
          }
        },
        {
          "args" : [

          ],
          "name" : "individual_id",
          "type" : {
            "kind" : "NON_NULL",
            "ofType" : {
              "kind" : "SCALAR",
              "name" : "bigint"
            }
          },
          "isDeprecated" : false
        },
        {
          "isDeprecated" : false,
          "args" : [

          ],
          "name" : "organization",
          "description" : "An object relationship",
          "type" : {
            "kind" : "NON_NULL",
            "ofType" : {
              "kind" : "OBJECT",
              "name" : "organizations"
            }
          }
        },
        {
          "args" : [

          ],
          "name" : "organization_id",
          "type" : {
            "kind" : "NON_NULL",
            "ofType" : {
              "kind" : "SCALAR",
              "name" : "bigint"
            }
          },
          "isDeprecated" : false
        }
      ],
      "kind" : "OBJECT",
      "name" : "organization_contact_individuals",
      "description" : "columns and relationships of \"organization_contact_individuals\""
    },
    {
      "fields" : [
        {
          "args" : [

          ],
          "name" : "aggregate",
          "type" : {
            "kind" : "OBJECT",
            "name" : "organization_contact_individuals_aggregate_fields"
          },
          "isDeprecated" : false
        },
        {
          "args" : [

          ],
          "name" : "nodes",
          "type" : {
            "kind" : "NON_NULL",
            "ofType" : {
              "kind" : "LIST",
              "ofType" : {
                "kind" : "NON_NULL",
                "ofType" : {
                  "kind" : "OBJECT",
                  "name" : "organization_contact_individuals"
                }
              }
            }
          },
          "isDeprecated" : false
        }
      ],
      "kind" : "OBJECT",
      "name" : "organization_contact_individuals_aggregate",
      "description" : "aggregated selection of \"organization_contact_individuals\""
    },
    {
      "fields" : [
        {
          "args" : [

          ],
          "name" : "date_formed",
          "type" : {
            "kind" : "SCALAR",
            "name" : "timestamptz"
          },
          "isDeprecated" : false
        },
        {
          "isDeprecated" : false,
          "args" : [
            {
              "name" : "distinct_on",
              "type" : {
                "kind" : "LIST",
                "ofType" : {
                  "kind" : "NON_NULL",
                  "ofType" : {
                    "kind" : "ENUM",
                    "name" : "organization_contact_individuals_select_column"
                  }
                }
              },
              "description" : "distinct select on columns"
            },
            {
              "name" : "limit",
              "type" : {
                "kind" : "SCALAR",
                "name" : "Int"
              },
              "description" : "limit the number of rows returned"
            },
            {
              "name" : "offset",
              "type" : {
                "kind" : "SCALAR",
                "name" : "Int"
              },
              "description" : "skip the first n rows. Use only with order_by"
            },
            {
              "name" : "order_by",
              "type" : {
                "kind" : "LIST",
                "ofType" : {
                  "kind" : "NON_NULL",
                  "ofType" : {
                    "kind" : "INPUT_OBJECT",
                    "name" : "organization_contact_individuals_order_by"
                  }
                }
              },
              "description" : "sort the rows by one or more columns"
            },
            {
              "name" : "where",
              "type" : {
                "kind" : "INPUT_OBJECT",
                "name" : "organization_contact_individuals_bool_exp"
              },
              "description" : "filter the rows returned"
            }
          ],
          "name" : "organization_contact_individuals",
          "description" : "An array relationship",
          "type" : {
            "kind" : "NON_NULL",
            "ofType" : {
              "kind" : "LIST",
              "ofType" : {
                "kind" : "NON_NULL",
                "ofType" : {
                  "kind" : "OBJECT",
                  "name" : "organization_contact_individuals"
                }
              }
            }
          }
        },
        {
          "isDeprecated" : false,
          "args" : [
            {
              "name" : "distinct_on",
              "type" : {
                "kind" : "LIST",
                "ofType" : {
                  "kind" : "NON_NULL",
                  "ofType" : {
                    "kind" : "ENUM",
                    "name" : "organization_contact_individuals_select_column"
                  }
                }
              },
              "description" : "distinct select on columns"
            },
            {
              "name" : "limit",
              "type" : {
                "kind" : "SCALAR",
                "name" : "Int"
              },
              "description" : "limit the number of rows returned"
            },
            {
              "name" : "offset",
              "type" : {
                "kind" : "SCALAR",
                "name" : "Int"
              },
              "description" : "skip the first n rows. Use only with order_by"
            },
            {
              "name" : "order_by",
              "type" : {
                "kind" : "LIST",
                "ofType" : {
                  "kind" : "NON_NULL",
                  "ofType" : {
                    "kind" : "INPUT_OBJECT",
                    "name" : "organization_contact_individuals_order_by"
                  }
                }
              },
              "description" : "sort the rows by one or more columns"
            },
            {
              "name" : "where",
              "type" : {
                "kind" : "INPUT_OBJECT",
                "name" : "organization_contact_individuals_bool_exp"
              },
              "description" : "filter the rows returned"
            }
          ],
          "name" : "organization_contact_individuals_aggregate",
          "description" : "An aggregated array relationship",
          "type" : {
            "kind" : "NON_NULL",
            "ofType" : {
              "kind" : "OBJECT",
              "name" : "organization_contact_individuals_aggregate"
            }
          }
        },
        {
          "args" : [

          ],
          "name" : "organization_id",
          "type" : {
            "kind" : "NON_NULL",
            "ofType" : {
              "kind" : "SCALAR",
              "name" : "bigint"
            }
          },
          "isDeprecated" : false
        },
        {
          "args" : [

          ],
          "name" : "organization_name",
          "type" : {
            "kind" : "SCALAR",
            "name" : "String"
          },
          "isDeprecated" : false
        },
        {
          "args" : [

          ],
          "name" : "uk_vat_number",
          "type" : {
            "kind" : "SCALAR",
            "name" : "String"
          },
          "isDeprecated" : false
        }
      ],
      "kind" : "OBJECT",
      "name" : "organizations",
      "description" : "columns and relationships of \"organizations\""
    },
    {
      "fields" : [
        {
          "args" : [

          ],
          "name" : "aggregate",
          "type" : {
            "kind" : "OBJECT",
            "name" : "organizations_aggregate_fields"
          },
          "isDeprecated" : false
        },
        {
          "args" : [

          ],
          "name" : "nodes",
          "type" : {
            "kind" : "NON_NULL",
            "ofType" : {
              "kind" : "LIST",
              "ofType" : {
                "kind" : "NON_NULL",
                "ofType" : {
                  "kind" : "OBJECT",
                  "name" : "organizations"
                }
              }
            }
          },
          "isDeprecated" : false
        }
      ],
      "kind" : "OBJECT",
      "name" : "organizations_aggregate",
      "description" : "aggregated selection of \"organizations\""
    },
    {
      "fields" : [
        {
          "isDeprecated" : false,
          "args" : [
            {
              "name" : "distinct_on",
              "type" : {
                "kind" : "LIST",
                "ofType" : {
                  "kind" : "NON_NULL",
                  "ofType" : {
                    "kind" : "ENUM",
                    "name" : "party_addresses_select_column"
                  }
                }
              },
              "description" : "distinct select on columns"
            },
            {
              "name" : "limit",
              "type" : {
                "kind" : "SCALAR",
                "name" : "Int"
              },
              "description" : "limit the number of rows returned"
            },
            {
              "name" : "offset",
              "type" : {
                "kind" : "SCALAR",
                "name" : "Int"
              },
              "description" : "skip the first n rows. Use only with order_by"
            },
            {
              "name" : "order_by",
              "type" : {
                "kind" : "LIST",
                "ofType" : {
                  "kind" : "NON_NULL",
                  "ofType" : {
                    "kind" : "INPUT_OBJECT",
                    "name" : "party_addresses_order_by"
                  }
                }
              },
              "description" : "sort the rows by one or more columns"
            },
            {
              "name" : "where",
              "type" : {
                "kind" : "INPUT_OBJECT",
                "name" : "party_addresses_bool_exp"
              },
              "description" : "filter the rows returned"
            }
          ],
          "name" : "party_addresses",
          "description" : "An array relationship",
          "type" : {
            "kind" : "NON_NULL",
            "ofType" : {
              "kind" : "LIST",
              "ofType" : {
                "kind" : "NON_NULL",
                "ofType" : {
                  "kind" : "OBJECT",
                  "name" : "party_addresses"
                }
              }
            }
          }
        },
        {
          "isDeprecated" : false,
          "args" : [
            {
              "name" : "distinct_on",
              "type" : {
                "kind" : "LIST",
                "ofType" : {
                  "kind" : "NON_NULL",
                  "ofType" : {
                    "kind" : "ENUM",
                    "name" : "party_addresses_select_column"
                  }
                }
              },
              "description" : "distinct select on columns"
            },
            {
              "name" : "limit",
              "type" : {
                "kind" : "SCALAR",
                "name" : "Int"
              },
              "description" : "limit the number of rows returned"
            },
            {
              "name" : "offset",
              "type" : {
                "kind" : "SCALAR",
                "name" : "Int"
              },
              "description" : "skip the first n rows. Use only with order_by"
            },
            {
              "name" : "order_by",
              "type" : {
                "kind" : "LIST",
                "ofType" : {
                  "kind" : "NON_NULL",
                  "ofType" : {
                    "kind" : "INPUT_OBJECT",
                    "name" : "party_addresses_order_by"
                  }
                }
              },
              "description" : "sort the rows by one or more columns"
            },
            {
              "name" : "where",
              "type" : {
                "kind" : "INPUT_OBJECT",
                "name" : "party_addresses_bool_exp"
              },
              "description" : "filter the rows returned"
            }
          ],
          "name" : "party_addresses_aggregate",
          "description" : "An aggregated array relationship",
          "type" : {
            "kind" : "NON_NULL",
            "ofType" : {
              "kind" : "OBJECT",
              "name" : "party_addresses_aggregate"
            }
          }
        },
        {
          "args" : [

          ],
          "name" : "party_email",
          "type" : {
            "kind" : "SCALAR",
            "name" : "String"
          },
          "isDeprecated" : false
        },
        {
          "isDeprecated" : false,
          "args" : [
            {
              "name" : "distinct_on",
              "type" : {
                "kind" : "LIST",
                "ofType" : {
                  "kind" : "NON_NULL",
                  "ofType" : {
                    "kind" : "ENUM",
                    "name" : "party_forms_select_column"
                  }
                }
              },
              "description" : "distinct select on columns"
            },
            {
              "name" : "limit",
              "type" : {
                "kind" : "SCALAR",
                "name" : "Int"
              },
              "description" : "limit the number of rows returned"
            },
            {
              "name" : "offset",
              "type" : {
                "kind" : "SCALAR",
                "name" : "Int"
              },
              "description" : "skip the first n rows. Use only with order_by"
            },
            {
              "name" : "order_by",
              "type" : {
                "kind" : "LIST",
                "ofType" : {
                  "kind" : "NON_NULL",
                  "ofType" : {
                    "kind" : "INPUT_OBJECT",
                    "name" : "party_forms_order_by"
                  }
                }
              },
              "description" : "sort the rows by one or more columns"
            },
            {
              "name" : "where",
              "type" : {
                "kind" : "INPUT_OBJECT",
                "name" : "party_forms_bool_exp"
              },
              "description" : "filter the rows returned"
            }
          ],
          "name" : "party_forms",
          "description" : "An array relationship",
          "type" : {
            "kind" : "NON_NULL",
            "ofType" : {
              "kind" : "LIST",
              "ofType" : {
                "kind" : "NON_NULL",
                "ofType" : {
                  "kind" : "OBJECT",
                  "name" : "party_forms"
                }
              }
            }
          }
        },
        {
          "isDeprecated" : false,
          "args" : [
            {
              "name" : "distinct_on",
              "type" : {
                "kind" : "LIST",
                "ofType" : {
                  "kind" : "NON_NULL",
                  "ofType" : {
                    "kind" : "ENUM",
                    "name" : "party_forms_select_column"
                  }
                }
              },
              "description" : "distinct select on columns"
            },
            {
              "name" : "limit",
              "type" : {
                "kind" : "SCALAR",
                "name" : "Int"
              },
              "description" : "limit the number of rows returned"
            },
            {
              "name" : "offset",
              "type" : {
                "kind" : "SCALAR",
                "name" : "Int"
              },
              "description" : "skip the first n rows. Use only with order_by"
            },
            {
              "name" : "order_by",
              "type" : {
                "kind" : "LIST",
                "ofType" : {
                  "kind" : "NON_NULL",
                  "ofType" : {
                    "kind" : "INPUT_OBJECT",
                    "name" : "party_forms_order_by"
                  }
                }
              },
              "description" : "sort the rows by one or more columns"
            },
            {
              "name" : "where",
              "type" : {
                "kind" : "INPUT_OBJECT",
                "name" : "party_forms_bool_exp"
              },
              "description" : "filter the rows returned"
            }
          ],
          "name" : "party_forms_aggregate",
          "description" : "An aggregated array relationship",
          "type" : {
            "kind" : "NON_NULL",
            "ofType" : {
              "kind" : "OBJECT",
              "name" : "party_forms_aggregate"
            }
          }
        },
        {
          "args" : [

          ],
          "name" : "party_id",
          "type" : {
            "kind" : "NON_NULL",
            "ofType" : {
              "kind" : "SCALAR",
              "name" : "bigint"
            }
          },
          "isDeprecated" : false
        },
        {
          "args" : [

          ],
          "name" : "party_phone",
          "type" : {
            "kind" : "SCALAR",
            "name" : "String"
          },
          "isDeprecated" : false
        },
        {
          "isDeprecated" : false,
          "args" : [
            {
              "name" : "distinct_on",
              "type" : {
                "kind" : "LIST",
                "ofType" : {
                  "kind" : "NON_NULL",
                  "ofType" : {
                    "kind" : "ENUM",
                    "name" : "party_services_select_column"
                  }
                }
              },
              "description" : "distinct select on columns"
            },
            {
              "name" : "limit",
              "type" : {
                "kind" : "SCALAR",
                "name" : "Int"
              },
              "description" : "limit the number of rows returned"
            },
            {
              "name" : "offset",
              "type" : {
                "kind" : "SCALAR",
                "name" : "Int"
              },
              "description" : "skip the first n rows. Use only with order_by"
            },
            {
              "name" : "order_by",
              "type" : {
                "kind" : "LIST",
                "ofType" : {
                  "kind" : "NON_NULL",
                  "ofType" : {
                    "kind" : "INPUT_OBJECT",
                    "name" : "party_services_order_by"
                  }
                }
              },
              "description" : "sort the rows by one or more columns"
            },
            {
              "name" : "where",
              "type" : {
                "kind" : "INPUT_OBJECT",
                "name" : "party_services_bool_exp"
              },
              "description" : "filter the rows returned"
            }
          ],
          "name" : "party_services",
          "description" : "An array relationship",
          "type" : {
            "kind" : "NON_NULL",
            "ofType" : {
              "kind" : "LIST",
              "ofType" : {
                "kind" : "NON_NULL",
                "ofType" : {
                  "kind" : "OBJECT",
                  "name" : "party_services"
                }
              }
            }
          }
        },
        {
          "isDeprecated" : false,
          "args" : [
            {
              "name" : "distinct_on",
              "type" : {
                "kind" : "LIST",
                "ofType" : {
                  "kind" : "NON_NULL",
                  "ofType" : {
                    "kind" : "ENUM",
                    "name" : "party_services_select_column"
                  }
                }
              },
              "description" : "distinct select on columns"
            },
            {
              "name" : "limit",
              "type" : {
                "kind" : "SCALAR",
                "name" : "Int"
              },
              "description" : "limit the number of rows returned"
            },
            {
              "name" : "offset",
              "type" : {
                "kind" : "SCALAR",
                "name" : "Int"
              },
              "description" : "skip the first n rows. Use only with order_by"
            },
            {
              "name" : "order_by",
              "type" : {
                "kind" : "LIST",
                "ofType" : {
                  "kind" : "NON_NULL",
                  "ofType" : {
                    "kind" : "INPUT_OBJECT",
                    "name" : "party_services_order_by"
                  }
                }
              },
              "description" : "sort the rows by one or more columns"
            },
            {
              "name" : "where",
              "type" : {
                "kind" : "INPUT_OBJECT",
                "name" : "party_services_bool_exp"
              },
              "description" : "filter the rows returned"
            }
          ],
          "name" : "party_services_aggregate",
          "description" : "An aggregated array relationship",
          "type" : {
            "kind" : "NON_NULL",
            "ofType" : {
              "kind" : "OBJECT",
              "name" : "party_services_aggregate"
            }
          }
        },
        {
          "args" : [

          ],
          "name" : "payment_method_code",
          "type" : {
            "kind" : "SCALAR",
            "name" : "String"
          },
          "isDeprecated" : false
        }
      ],
      "kind" : "OBJECT",
      "name" : "parties",
      "description" : "columns and relationships of \"parties\""
    },
    {
      "fields" : [
        {
          "args" : [

          ],
          "name" : "aggregate",
          "type" : {
            "kind" : "OBJECT",
            "name" : "parties_aggregate_fields"
          },
          "isDeprecated" : false
        },
        {
          "args" : [

          ],
          "name" : "nodes",
          "type" : {
            "kind" : "NON_NULL",
            "ofType" : {
              "kind" : "LIST",
              "ofType" : {
                "kind" : "NON_NULL",
                "ofType" : {
                  "kind" : "OBJECT",
                  "name" : "parties"
                }
              }
            }
          },
          "isDeprecated" : false
        }
      ],
      "kind" : "OBJECT",
      "name" : "parties_aggregate",
      "description" : "aggregated selection of \"parties\""
    },
    {
      "fields" : [
        {
          "isDeprecated" : false,
          "args" : [

          ],
          "name" : "address",
          "description" : "An object relationship",
          "type" : {
            "kind" : "NON_NULL",
            "ofType" : {
              "kind" : "OBJECT",
              "name" : "addresses"
            }
          }
        },
        {
          "args" : [

          ],
          "name" : "address_id",
          "type" : {
            "kind" : "NON_NULL",
            "ofType" : {
              "kind" : "SCALAR",
              "name" : "bigint"
            }
          },
          "isDeprecated" : false
        },
        {
          "args" : [

          ],
          "name" : "address_type_code",
          "type" : {
            "kind" : "SCALAR",
            "name" : "String"
          },
          "isDeprecated" : false
        },
        {
          "args" : [

          ],
          "name" : "date_address_from",
          "type" : {
            "kind" : "SCALAR",
            "name" : "timestamptz"
          },
          "isDeprecated" : false
        },
        {
          "args" : [

          ],
          "name" : "date_address_to",
          "type" : {
            "kind" : "SCALAR",
            "name" : "timestamptz"
          },
          "isDeprecated" : false
        },
        {
          "isDeprecated" : false,
          "args" : [

          ],
          "name" : "party",
          "description" : "An object relationship",
          "type" : {
            "kind" : "NON_NULL",
            "ofType" : {
              "kind" : "OBJECT",
              "name" : "parties"
            }
          }
        },
        {
          "args" : [

          ],
          "name" : "party_id",
          "type" : {
            "kind" : "NON_NULL",
            "ofType" : {
              "kind" : "SCALAR",
              "name" : "bigint"
            }
          },
          "isDeprecated" : false
        }
      ],
      "kind" : "OBJECT",
      "name" : "party_addresses",
      "description" : "columns and relationships of \"party_addresses\""
    },
    {
      "fields" : [
        {
          "args" : [

          ],
          "name" : "aggregate",
          "type" : {
            "kind" : "OBJECT",
            "name" : "party_addresses_aggregate_fields"
          },
          "isDeprecated" : false
        },
        {
          "args" : [

          ],
          "name" : "nodes",
          "type" : {
            "kind" : "NON_NULL",
            "ofType" : {
              "kind" : "LIST",
              "ofType" : {
                "kind" : "NON_NULL",
                "ofType" : {
                  "kind" : "OBJECT",
                  "name" : "party_addresses"
                }
              }
            }
          },
          "isDeprecated" : false
        }
      ],
      "kind" : "OBJECT",
      "name" : "party_addresses_aggregate",
      "description" : "aggregated selection of \"party_addresses\""
    },
    {
      "fields" : [
        {
          "args" : [

          ],
          "name" : "date_completion_started",
          "type" : {
            "kind" : "SCALAR",
            "name" : "timestamptz"
          },
          "isDeprecated" : false
        },
        {
          "args" : [

          ],
          "name" : "date_fully_completed",
          "type" : {
            "kind" : "SCALAR",
            "name" : "timestamptz"
          },
          "isDeprecated" : false
        },
        {
          "isDeprecated" : false,
          "args" : [

          ],
          "name" : "form",
          "description" : "An object relationship",
          "type" : {
            "kind" : "NON_NULL",
            "ofType" : {
              "kind" : "OBJECT",
              "name" : "forms"
            }
          }
        },
        {
          "args" : [

          ],
          "name" : "form_id",
          "type" : {
            "kind" : "NON_NULL",
            "ofType" : {
              "kind" : "SCALAR",
              "name" : "bigint"
            }
          },
          "isDeprecated" : false
        },
        {
          "args" : [

          ],
          "name" : "form_status_code",
          "type" : {
            "kind" : "SCALAR",
            "name" : "String"
          },
          "isDeprecated" : false
        },
        {
          "isDeprecated" : false,
          "args" : [

          ],
          "name" : "party",
          "description" : "An object relationship",
          "type" : {
            "kind" : "NON_NULL",
            "ofType" : {
              "kind" : "OBJECT",
              "name" : "parties"
            }
          }
        },
        {
          "args" : [

          ],
          "name" : "party_id",
          "type" : {
            "kind" : "NON_NULL",
            "ofType" : {
              "kind" : "SCALAR",
              "name" : "bigint"
            }
          },
          "isDeprecated" : false
        }
      ],
      "kind" : "OBJECT",
      "name" : "party_forms",
      "description" : "columns and relationships of \"party_forms\""
    },
    {
      "fields" : [
        {
          "args" : [

          ],
          "name" : "aggregate",
          "type" : {
            "kind" : "OBJECT",
            "name" : "party_forms_aggregate_fields"
          },
          "isDeprecated" : false
        },
        {
          "args" : [

          ],
          "name" : "nodes",
          "type" : {
            "kind" : "NON_NULL",
            "ofType" : {
              "kind" : "LIST",
              "ofType" : {
                "kind" : "NON_NULL",
                "ofType" : {
                  "kind" : "OBJECT",
                  "name" : "party_forms"
                }
              }
            }
          },
          "isDeprecated" : false
        }
      ],
      "kind" : "OBJECT",
      "name" : "party_forms_aggregate",
      "description" : "aggregated selection of \"party_forms\""
    },
    {
      "fields" : [
        {
          "args" : [

          ],
          "name" : "booking_id",
          "type" : {
            "kind" : "SCALAR",
            "name" : "bigint"
          },
          "isDeprecated" : false
        },
        {
          "args" : [

          ],
          "name" : "booking_made_date",
          "type" : {
            "kind" : "SCALAR",
            "name" : "timestamptz"
          },
          "isDeprecated" : false
        },
        {
          "args" : [

          ],
          "name" : "customer_id",
          "type" : {
            "kind" : "SCALAR",
            "name" : "bigint"
          },
          "isDeprecated" : false
        },
        {
          "isDeprecated" : false,
          "args" : [

          ],
          "name" : "party",
          "description" : "An object relationship",
          "type" : {
            "kind" : "OBJECT",
            "name" : "parties"
          }
        },
        {
          "isDeprecated" : false,
          "args" : [

          ],
          "name" : "service",
          "description" : "An object relationship",
          "type" : {
            "kind" : "OBJECT",
            "name" : "services"
          }
        },
        {
          "args" : [

          ],
          "name" : "service_datetime",
          "type" : {
            "kind" : "SCALAR",
            "name" : "timestamptz"
          },
          "isDeprecated" : false
        },
        {
          "args" : [

          ],
          "name" : "service_id",
          "type" : {
            "kind" : "SCALAR",
            "name" : "bigint"
          },
          "isDeprecated" : false
        }
      ],
      "kind" : "OBJECT",
      "name" : "party_services",
      "description" : "columns and relationships of \"party_services\""
    },
    {
      "fields" : [
        {
          "args" : [

          ],
          "name" : "aggregate",
          "type" : {
            "kind" : "OBJECT",
            "name" : "party_services_aggregate_fields"
          },
          "isDeprecated" : false
        },
        {
          "args" : [

          ],
          "name" : "nodes",
          "type" : {
            "kind" : "NON_NULL",
            "ofType" : {
              "kind" : "LIST",
              "ofType" : {
                "kind" : "NON_NULL",
                "ofType" : {
                  "kind" : "OBJECT",
                  "name" : "party_services"
                }
              }
            }
          },
          "isDeprecated" : false
        }
      ],
      "kind" : "OBJECT",
      "name" : "party_services_aggregate",
      "description" : "aggregated selection of \"party_services\""
    },
    {
      "fields" : [
        {
          "isDeprecated" : false,
          "args" : [
            {
              "name" : "distinct_on",
              "type" : {
                "kind" : "LIST",
                "ofType" : {
                  "kind" : "NON_NULL",
                  "ofType" : {
                    "kind" : "ENUM",
                    "name" : "forms_select_column"
                  }
                }
              },
              "description" : "distinct select on columns"
            },
            {
              "name" : "limit",
              "type" : {
                "kind" : "SCALAR",
                "name" : "Int"
              },
              "description" : "limit the number of rows returned"
            },
            {
              "name" : "offset",
              "type" : {
                "kind" : "SCALAR",
                "name" : "Int"
              },
              "description" : "skip the first n rows. Use only with order_by"
            },
            {
              "name" : "order_by",
              "type" : {
                "kind" : "LIST",
                "ofType" : {
                  "kind" : "NON_NULL",
                  "ofType" : {
                    "kind" : "INPUT_OBJECT",
                    "name" : "forms_order_by"
                  }
                }
              },
              "description" : "sort the rows by one or more columns"
            },
            {
              "name" : "where",
              "type" : {
                "kind" : "INPUT_OBJECT",
                "name" : "forms_bool_exp"
              },
              "description" : "filter the rows returned"
            }
          ],
          "name" : "forms",
          "description" : "An array relationship",
          "type" : {
            "kind" : "NON_NULL",
            "ofType" : {
              "kind" : "LIST",
              "ofType" : {
                "kind" : "NON_NULL",
                "ofType" : {
                  "kind" : "OBJECT",
                  "name" : "forms"
                }
              }
            }
          }
        },
        {
          "isDeprecated" : false,
          "args" : [
            {
              "name" : "distinct_on",
              "type" : {
                "kind" : "LIST",
                "ofType" : {
                  "kind" : "NON_NULL",
                  "ofType" : {
                    "kind" : "ENUM",
                    "name" : "forms_select_column"
                  }
                }
              },
              "description" : "distinct select on columns"
            },
            {
              "name" : "limit",
              "type" : {
                "kind" : "SCALAR",
                "name" : "Int"
              },
              "description" : "limit the number of rows returned"
            },
            {
              "name" : "offset",
              "type" : {
                "kind" : "SCALAR",
                "name" : "Int"
              },
              "description" : "skip the first n rows. Use only with order_by"
            },
            {
              "name" : "order_by",
              "type" : {
                "kind" : "LIST",
                "ofType" : {
                  "kind" : "NON_NULL",
                  "ofType" : {
                    "kind" : "INPUT_OBJECT",
                    "name" : "forms_order_by"
                  }
                }
              },
              "description" : "sort the rows by one or more columns"
            },
            {
              "name" : "where",
              "type" : {
                "kind" : "INPUT_OBJECT",
                "name" : "forms_bool_exp"
              },
              "description" : "filter the rows returned"
            }
          ],
          "name" : "forms_aggregate",
          "description" : "An aggregated array relationship",
          "type" : {
            "kind" : "NON_NULL",
            "ofType" : {
              "kind" : "OBJECT",
              "name" : "forms_aggregate"
            }
          }
        },
        {
          "isDeprecated" : false,
          "args" : [
            {
              "name" : "distinct_on",
              "type" : {
                "kind" : "LIST",
                "ofType" : {
                  "kind" : "NON_NULL",
                  "ofType" : {
                    "kind" : "ENUM",
                    "name" : "party_services_select_column"
                  }
                }
              },
              "description" : "distinct select on columns"
            },
            {
              "name" : "limit",
              "type" : {
                "kind" : "SCALAR",
                "name" : "Int"
              },
              "description" : "limit the number of rows returned"
            },
            {
              "name" : "offset",
              "type" : {
                "kind" : "SCALAR",
                "name" : "Int"
              },
              "description" : "skip the first n rows. Use only with order_by"
            },
            {
              "name" : "order_by",
              "type" : {
                "kind" : "LIST",
                "ofType" : {
                  "kind" : "NON_NULL",
                  "ofType" : {
                    "kind" : "INPUT_OBJECT",
                    "name" : "party_services_order_by"
                  }
                }
              },
              "description" : "sort the rows by one or more columns"
            },
            {
              "name" : "where",
              "type" : {
                "kind" : "INPUT_OBJECT",
                "name" : "party_services_bool_exp"
              },
              "description" : "filter the rows returned"
            }
          ],
          "name" : "party_services",
          "description" : "An array relationship",
          "type" : {
            "kind" : "NON_NULL",
            "ofType" : {
              "kind" : "LIST",
              "ofType" : {
                "kind" : "NON_NULL",
                "ofType" : {
                  "kind" : "OBJECT",
                  "name" : "party_services"
                }
              }
            }
          }
        },
        {
          "isDeprecated" : false,
          "args" : [
            {
              "name" : "distinct_on",
              "type" : {
                "kind" : "LIST",
                "ofType" : {
                  "kind" : "NON_NULL",
                  "ofType" : {
                    "kind" : "ENUM",
                    "name" : "party_services_select_column"
                  }
                }
              },
              "description" : "distinct select on columns"
            },
            {
              "name" : "limit",
              "type" : {
                "kind" : "SCALAR",
                "name" : "Int"
              },
              "description" : "limit the number of rows returned"
            },
            {
              "name" : "offset",
              "type" : {
                "kind" : "SCALAR",
                "name" : "Int"
              },
              "description" : "skip the first n rows. Use only with order_by"
            },
            {
              "name" : "order_by",
              "type" : {
                "kind" : "LIST",
                "ofType" : {
                  "kind" : "NON_NULL",
                  "ofType" : {
                    "kind" : "INPUT_OBJECT",
                    "name" : "party_services_order_by"
                  }
                }
              },
              "description" : "sort the rows by one or more columns"
            },
            {
              "name" : "where",
              "type" : {
                "kind" : "INPUT_OBJECT",
                "name" : "party_services_bool_exp"
              },
              "description" : "filter the rows returned"
            }
          ],
          "name" : "party_services_aggregate",
          "description" : "An aggregated array relationship",
          "type" : {
            "kind" : "NON_NULL",
            "ofType" : {
              "kind" : "OBJECT",
              "name" : "party_services_aggregate"
            }
          }
        },
        {
          "args" : [

          ],
          "name" : "service_descriptio",
          "type" : {
            "kind" : "SCALAR",
            "name" : "String"
          },
          "isDeprecated" : false
        },
        {
          "args" : [

          ],
          "name" : "service_id",
          "type" : {
            "kind" : "NON_NULL",
            "ofType" : {
              "kind" : "SCALAR",
              "name" : "bigint"
            }
          },
          "isDeprecated" : false
        },
        {
          "args" : [

          ],
          "name" : "service_name",
          "type" : {
            "kind" : "SCALAR",
            "name" : "String"
          },
          "isDeprecated" : false
        },
        {
          "args" : [

          ],
          "name" : "service_type_code",
          "type" : {
            "kind" : "SCALAR",
            "name" : "String"
          },
          "isDeprecated" : false
        }
      ],
      "kind" : "OBJECT",
      "name" : "services",
      "description" : "columns and relationships of \"services\""
    },
    {
      "fields" : [
        {
          "args" : [

          ],
          "name" : "aggregate",
          "type" : {
            "kind" : "OBJECT",
            "name" : "services_aggregate_fields"
          },
          "isDeprecated" : false
        },
        {
          "args" : [

          ],
          "name" : "nodes",
          "type" : {
            "kind" : "NON_NULL",
            "ofType" : {
              "kind" : "LIST",
              "ofType" : {
                "kind" : "NON_NULL",
                "ofType" : {
                  "kind" : "OBJECT",
                  "name" : "services"
                }
              }
            }
          },
          "isDeprecated" : false
        }
      ],
      "kind" : "OBJECT",
      "name" : "services_aggregate",
      "description" : "aggregated selection of \"services\""
    }
  ],
  "arguments" : [
    {
      "name" : "distinct_on",
      "type" : {
        "kind" : "LIST",
        "ofType" : {
          "kind" : "NON_NULL",
          "ofType" : {
            "kind" : "ENUM",
            "name" : "addresses_select_column"
          }
        }
      },
      "description" : "distinct select on columns"
    },
    {
      "name" : "limit",
      "type" : {
        "kind" : "SCALAR",
        "name" : "Int"
      },
      "description" : "limit the number of rows returned"
    },
    {
      "name" : "offset",
      "type" : {
        "kind" : "SCALAR",
        "name" : "Int"
      },
      "description" : "skip the first n rows. Use only with order_by"
    },
    {
      "name" : "order_by",
      "type" : {
        "kind" : "LIST",
        "ofType" : {
          "kind" : "NON_NULL",
          "ofType" : {
            "kind" : "INPUT_OBJECT",
            "name" : "addresses_order_by"
          }
        }
      },
      "description" : "sort the rows by one or more columns"
    },
    {
      "name" : "where",
      "type" : {
        "kind" : "INPUT_OBJECT",
        "name" : "addresses_bool_exp"
      },
      "description" : "filter the rows returned"
    }
  ]
}